{
    "parse_time": "2025-04-18 03:28:00",
    "path": "https://www.cnvd.org.cn/flaw/show/CNVD-2025-07475",
    "spider_time": 1744946880896,
    "name": "新华三技术有限公司H3C IMC存在文件上传漏洞",
    "cnvd": "CNVD-2025-07475",
    "publish": "2025-04-13",
    "severity": "高",
    "cvss_vector": "AV:N/AC:L/Au:N/C:C/I:C/A:C",
    "product": "[\"\\u65b0\\u534e\\u4e09\\u6280\\u672f\\u6709\\u9650\\u516c\\u53f8 H3C iMC\"]",
    "cve": null,
    "description": "新华三技术有限公司是一家全球领先的数字化解决方案领导者。新华三技术有限公司H3C IMC存在文件上传漏洞，攻击者可利用该漏洞获取服务器控制权。",
    "flaw_type": "通用型漏洞",
    "reference": null,
    "solution": "厂商尚未发布漏洞修复程序，请及时关注更新：\nhttps://www.h3c.com/",
    "patch": "(无补丁信息)",
    "verify": "已验证",
    "submit_time": "2025-02-27",
    "open_time": "2025-04-18",
    "update_time": "2025-04-18",
    "data_summary": "6f40a59bba79b8757d8a94d68f855bc4"
}