{
    "parse_time": "2025-03-04 16:19:49",
    "path": "https://www.cnvd.org.cn/flaw/show/CNVD-2025-03636",
    "spider_time": 1741105189582,
    "name": null,
    "cnvd": null,
    "publish": null,
    "severity": null,
    "cvss_vector": null,
    "product": "null",
    "cve": null,
    "description": null,
    "flaw_type": null,
    "reference": null,
    "solution": null,
    "patch": null,
    "verify": null,
    "submit_time": null,
    "open_time": null,
    "update_time": null,
    "data_summary": "0ed93642f8bf3aa4ca36e131b9eb0b06"
}