{
    "parse_time": "2025-05-21 22:03:31",
    "path": "https://www.cnvd.org.cn/flaw/show/CNVD-2025-09455",
    "spider_time": 1747865011065,
    "name": "新华三技术有限公司H3C Magic R3010千兆双频Wi-Fi 6路由器存在逻辑缺陷漏洞",
    "cnvd": "CNVD-2025-09455",
    "publish": "2025-05-11",
    "severity": "高",
    "cvss_vector": "AV:N/AC:L/Au:N/C:C/I:C/A:C",
    "product": "[\"\\u65b0\\u534e\\u4e09\\u6280\\u672f\\u6709\\u9650\\u516c\\u53f8 H3C Magic R3010\\u5343\\u5146\\u53cc\\u9891Wi-Fi 6\\u8def\\u7531\\u5668 <=V100R004\"]",
    "cve": null,
    "description": "新华三技术有限公司是一家全球领先的数字化解决方案领导者。新华三技术有限公司H3C Magic R3010千兆双频Wi-Fi 6路由器存在逻辑缺陷漏洞，攻击者可利用该漏洞获取敏感信息。",
    "flaw_type": "通用型漏洞",
    "reference": null,
    "solution": "厂商尚未发布漏洞修复程序，请及时关注更新：\nhttps://www.h3c.com/",
    "patch": "(无补丁信息)",
    "verify": "已验证",
    "submit_time": "2025-03-27",
    "open_time": "2025-05-13",
    "update_time": "2025-05-13",
    "data_summary": "56dc909d1422c48862e9fa98e861b459"
}